aerismodsdk/__init__.py
aerismodsdk/cli.py
aerismodsdk/manufacturer.py
aerismodsdk/model/shoulder_tap.py
aerismodsdk/modulefactory.py
aerismodsdk/modules/__init__.py
aerismodsdk/modules/module.py
aerismodsdk/modules/quectel.py
aerismodsdk/modules/telit.py
aerismodsdk/modules/ublox.py
aerismodsdk/utils/__init__.py
aerismodsdk/utils/aerisutils.py
aerismodsdk/utils/gpioutils.py
aerismodsdk/utils/loggerutils.py
aerismodsdk/utils/rmutils.py
aerismodsdk/utils/shoulder_tap.py
aerismodsdk-0.1.5.dist-info/entry_points.txt
aerismodsdk-0.1.5.dist-info/LICENSE
aerismodsdk-0.1.5.dist-info/WHEEL
aerismodsdk-0.1.5.dist-info/METADATA
aerismodsdk-0.1.5.dist-info/RECORD
